{
  "index": {
    "title": "主页",
    "type": "page",
    "display": "hidden",
    "theme": {
      "timestamp": false,
      "layout": "raw"
    }
  },
  "docs": {
    "title": "文档",
    "type": "page"
  },
  "blog": {
    "title": "博客",
    "type": "page",
    "theme": {
      "sidebar": false,
      "timestamp": false,
      "typesetting": "article"
    }
  },
  "about": {
    "title": "关于",
    "type": "page",
    "theme": {
      "sidebar": false,
      "typesetting": "article"
    }
  },
  "404": {
    "type": "page",
    "theme": {
      "sidebar": false,
      "typesetting": "article"
    }
  },
  "brand": {
    "type": "page",
    "display": "hidden",
    "theme": {
      "sidebar": false,
      "timestamp": false,
      "typesetting": "article"
    }
  },
  "blog-template": {
    "type": "page",
    "display": "hidden"
  }
}
